dijkstra/__init__.py
dijkstra/dijkstra.py
dijkstra/graph.py
dijkstra-0.2.1.dist-info/LICENSE
dijkstra-0.2.1.dist-info/METADATA
dijkstra-0.2.1.dist-info/WHEEL
dijkstra-0.2.1.dist-info/top_level.txt
dijkstra-0.2.1.dist-info/RECORD
