Metadata-Version: 2.1
Name: dijkstra
Version: 0.2.1
Summary: dijkstra is a native Python implementation of famous Dijkstra's shortest path algorithm. The implemented algorithm can be used to analyze reasonably large networks. The primary goal in design is the clarity of the program code. Thus, program code tends to be more educational than effective.
Home-page: https://github.com/ahojukka5/dijkstra
Author: Jukka Aho
Author-email: ahojukka5@gmail.com
License: UNKNOWN
Platform: UNKNOWN
Classifier: Programming Language :: Python :: 3
Classifier: License :: OSI Approved :: MIT License
Classifier: Operating System :: OS Independent
Provides-Extra: test
